src/__init__.py
src/assistant_controller.py
src/book_controller.py
src/main.py
src/models/__init__.py
src/models/address_book.py
src/models/fields.py
src/models/record.py
assistant_bot-0.8.6.dist-info/METADATA
assistant_bot-0.8.6.dist-info/WHEEL
assistant_bot-0.8.6.dist-info/entry_points.txt
assistant_bot-0.8.6.dist-info/top_level.txt
assistant_bot-0.8.6.dist-info/RECORD
