Metadata-Version: 2.1
Name: assistant-bot
Version: 0.8.6
Summary: The personal assistant bot
Home-page: https://github.com/vladshein/project-team-04
Author: project-team-04
Classifier: Programming Language :: Python :: 3
Classifier: License :: OSI Approved :: MIT License
Classifier: Operating System :: OS Independent
Requires-Python: >=3.6
Requires-Dist: prompt-toolkit ==3.0.47
Requires-Dist: wcwidth ==0.2.13
Requires-Dist: tabulate ==0.9.0
